Metadata-Version: 2.1
Name: google-cloud-dataproc-momovn
Version: 5.0.3
Summary: Google Cloud Dataproc API client library
Home-page: https://github.com/googleapis/python-dataproc
Author: Google LLC
Author-email: googleapis-packages@google.com
License: Apache 2.0
Platform: Posix; MacOS X; Windows
Classifier: Development Status :: 5 - Production/Stable
Classifier: Intended Audience :: Developers
Classifier: License :: OSI Approved :: Apache Software License
Classifier: Programming Language :: Python
Classifier: Programming Language :: Python :: 3
Classifier: Programming Language :: Python :: 3.7
Classifier: Programming Language :: Python :: 3.8
Classifier: Programming Language :: Python :: 3.9
Classifier: Programming Language :: Python :: 3.10
Classifier: Operating System :: OS Independent
Classifier: Topic :: Internet
Requires-Python: >=3.7
License-File: LICENSE
Requires-Dist: google-api-core[grpc] (!=2.0.*,!=2.1.*,!=2.2.*,!=2.3.*,!=2.4.*,!=2.5.*,!=2.6.*,!=2.7.*,<3.0.0dev,>=1.32.0)
Requires-Dist: proto-plus (<2.0.0dev,>=1.22.0)
Requires-Dist: protobuf (!=3.20.0,!=3.20.1,!=4.21.0,!=4.21.1,!=4.21.2,!=4.21.3,!=4.21.4,!=4.21.5,<5.0.0dev,>=3.19.5)
Provides-Extra: libcst
Requires-Dist: libcst (>=0.2.5) ; extra == 'libcst'
